gamma_books.py
gamma_books-1.1.0.dist-info/METADATA
gamma_books-1.1.0.dist-info/WHEEL
gamma_books-1.1.0.dist-info/top_level.txt
gamma_books-1.1.0.dist-info/RECORD
