Metadata-Version: 2.4
Name: gamma-books
Version: 1.1.0
Requires-Dist: web3
Requires-Dist: numpy
Requires-Dist: eth-utils
Requires-Dist: matplotlib
